{
  "app": {
    "bot": {
      "token": "",
      "chat": "",
      "replyTo": ""
    },
    "base": {
      "lang": "en",
      "messenger": "email",
      "allureFolder": "allure-report/",
      "allureLinkPath": "allure",
      "chart": true,
      "chartName": "",
      "project": ""
    },
    "mail": {
      "host": "smtp.gmail.com",
      "port": "465",
      "username": "ismagilov.vel@gmail.com",
      "password": "password_here",
      "enableSSL": true,
      "from": "ismagilov.vel@gmail.com",
      "recipient": "ismagilov.vel@gmail.com"
    },
    "mattermost": {
      "url": ""
    },
    "proxy": {
      "host": "",
      "port": 0,
      "username": "",
      "password": ""
    },
    "skype": {
      "appId": "",
      "appSecret": "",
      "serviceUrl": "",
      "conversationId": "",
      "botId": "",
      "botName": ""
    }
  }
}
